incharge/__init__.py
incharge/api.py
incharge/const.py
incharge/exceptions.py
incharge-1.0.3.dist-info/LICENSE
incharge-1.0.3.dist-info/METADATA
incharge-1.0.3.dist-info/WHEEL
incharge-1.0.3.dist-info/top_level.txt
incharge-1.0.3.dist-info/RECORD
