Metadata-Version: 2.1
Name: incharge
Version: 1.0.3
Summary: A package to talk to the VattenFall InCharge API's
Home-page: https://github.com/tgriek/incharge
Author: Tim van Grieken
Author-email: tgriek@gmail.com
License: MIT
Classifier: Programming Language :: Python :: 3
Classifier: License :: OSI Approved :: MIT License
Classifier: Operating System :: OS Independent
License-File: LICENSE
Requires-Dist: requests
